huishi/__init__.py
huishi-1.0.0.dist-info/LICENSE
huishi-1.0.0.dist-info/METADATA
huishi-1.0.0.dist-info/WHEEL
huishi-1.0.0.dist-info/top_level.txt
huishi-1.0.0.dist-info/RECORD
