Metadata-Version: 2.1
Name: huishi
Version: 1.0.0
Summary: A package that can let you create a poem by AI
Home-page: https://gitee.com/wangshixincheng/keywords_to_poem
Author: ZenMeHuiShiNe
Author-email: 2020302111360@whu.edu.cn
Classifier: Programming Language :: Python :: 3
Classifier: License :: OSI Approved :: MIT License
Classifier: Operating System :: OS Independent
License-File: LICENSE
